Metadata-Version: 2.1
Name: joyrec
Version: 0.0.1
Summary: To Build Your Recommad System
Home-page: https://github.com/me/myproject
Author: Asher Wang
Author-email: hi_wangtao@163.com
License: MIT
Classifier: License :: OSI Approved :: MIT License
Classifier: Programming Language :: Python
Classifier: Programming Language :: Python :: 3
Classifier: Programming Language :: Python :: 3.6
Classifier: Programming Language :: Python :: Implementation :: CPython
Classifier: Programming Language :: Python :: Implementation :: PyPy
Requires-Python: >=3.7.0
License-File: LICENSE
